Metadata-Version: 2.1
Name: pdrive
Version: 0.8.2
Summary: A simple file manager
Home-page: https://github.com/huyng/pdrive
Author: Huy Nguyen
Author-email: 121183+huyng@users.noreply.github.com
License: UNKNOWN
Platform: UNKNOWN
